bin/grest
docs/about.md
docs/application.md
docs/authentication_authorization.md
docs/configuration.md
docs/custom_endpoints.md
docs/deployment.md
docs/index.md
docs/installation.md
docs/license.md
docs/logging.md
docs/models.md
docs/routes.md
docs/tutorial.md
docs/views.md
docs/img/favicon.ico
docs/img/gREST-logo.png
examples/__init__.py
examples/app.py
examples/extended_app.py
grest/__init__.py
grest/auth.py
grest/exceptions.py
grest/global_config.py
grest/grest.py
grest/messages.py
grest/models.py
grest/utils.py
grest/validation.py
grest/verbs/__init__.py
grest/verbs/delete.py
grest/verbs/get.py
grest/verbs/index.py
grest/verbs/patch.py
grest/verbs/post.py
grest/verbs/put.py
pygrest-1.4.0.data/scripts/grest
tests/__init__.py
tests/test_app.py
tests/test_extended_app.py
tests/test_validation_rules_property.py
pygrest-1.4.0.dist-info/LICENSE
pygrest-1.4.0.dist-info/METADATA
pygrest-1.4.0.dist-info/WHEEL
pygrest-1.4.0.dist-info/top_level.txt
pygrest-1.4.0.dist-info/RECORD
