Metadata-Version: 2.1
Name: pygrest
Version: 1.4.0
Summary: Build REST APIs with Neo4j and Flask, as quickly as possible!
Home-page: https://github.com/mostafa/GRest
Author: Mostafa Moradian
Author-email: mostafamoradian0@gmail.com
License: GPLv3
Platform: UNKNOWN
Classifier: Development Status :: 5 - Production/Stable
Classifier: Intended Audience :: Developers
Classifier: Framework :: Flask
Classifier: Topic :: Software Development :: Libraries
Classifier: License :: OSI Approved :: GNU General Public License v3 (GPLv3)
Classifier: Programming Language :: Python :: 2
Classifier: Programming Language :: Python :: 2.7
Classifier: Programming Language :: Python :: 3
Classifier: Programming Language :: Python :: 3.6
Classifier: Programming Language :: Python :: 3.7
Requires-Dist: Autologging (==1.3.2)
Requires-Dist: dicttoxml (==1.7.4)
Requires-Dist: Flask (==1.0.3)
Requires-Dist: Flask-Classful (==0.14.2)
Requires-Dist: inflection (==0.3.1)
Requires-Dist: MarkupSafe (==1.1.1)
Requires-Dist: neomodel (==3.3.1)
Requires-Dist: pytest (==4.5.0)
Requires-Dist: pytest-flask (==0.15.0)
Requires-Dist: requests (==2.22.0)
Requires-Dist: setuptools (==41.0.1)
Requires-Dist: Unidecode (==1.0.23)
Requires-Dist: webargs (==5.3.1)
Requires-Dist: Werkzeug (==0.15.4)
Requires-Dist: PyYAML (==5.1)
Requires-Dist: simplejson (==3.16.0)
Requires-Dist: pathlib2 (==2.3.3)
Requires-Dist: cookiecutter (==1.6.0)
